highlyprobable
